joltos/__init__.py
joltos/image.py
joltos/qemu.py
joltos/tasks.py
joltos/toolchain.py
joltos/version.py
joltos/templates/Dockerfile.alpine
joltos/templates/Dockerfile.alpine.images
joltos/templates/Dockerfile.alpine.packages
joltos/templates/Dockerfile.alpine.tools
joltos/templates/Dockerfile.common.commands
joltos/templates/Dockerfile.common.files
joltos/templates/Dockerfile.common.images
joltos/templates/Dockerfile.common.publish
joltos/templates/Dockerfile.common.tools
joltos/templates/Dockerfile.common.users
joltos/templates/Dockerfile.debian
joltos/templates/Dockerfile.debian.images
joltos/templates/Dockerfile.debian.packages
joltos/templates/Dockerfile.debian.tools
joltos-1.0.dist-info/METADATA
joltos-1.0.dist-info/WHEEL
joltos-1.0.dist-info/top_level.txt
joltos-1.0.dist-info/RECORD
