Metadata-Version: 2.1
Name: joltos
Version: 1.0
Summary: OS Image Builder
Home-page: https://github.com/srand/joltos
Author: Robert Andersson
Author-email: srand@github.com
License: UNKNOWN
Keywords: alpine,debian
Platform: UNKNOWN
Classifier: Development Status :: 5 - Production/Stable
Classifier: Intended Audience :: Developers
Classifier: Topic :: Software Development :: Build Tools
Classifier: License :: OSI Approved :: GNU General Public License v2 (GPLv2)
Classifier: Operating System :: POSIX
Classifier: Programming Language :: Python :: 3
Requires-Dist: jolt
